pymp4/__init__.py
pymp4/cli.py
pymp4/exceptions.py
pymp4/parser.py
pymp4/tools/__init__.py
pymp4/util.py
rlaphoenix_pymp4-1.5.0.dist-info/entry_points.txt
rlaphoenix_pymp4-1.5.0.dist-info/LICENSE
rlaphoenix_pymp4-1.5.0.dist-info/METADATA
rlaphoenix_pymp4-1.5.0.dist-info/WHEEL
rlaphoenix_pymp4-1.5.0.dist-info/RECORD
