Metadata-Version: 2.1
Name: rlaphoenix-pymp4
Version: 1.5.0
Summary: A Python parser for MP4 boxes
Home-page: https://github.com/rlaphoenix/pymp4
License: Apache-2.0
Author: beardypig
Author-email: git@beardypig.com
Requires-Python: >=2.7, !=3.0.*, !=3.1.*, !=3.2.*
Classifier: Development Status :: 4 - Beta
Classifier: Environment :: Console
Classifier: Intended Audience :: Developers
Classifier: License :: OSI Approved :: Apache Software License
Classifier: Natural Language :: English
Classifier: Operating System :: OS Independent
Classifier: Programming Language :: Python :: 2
Classifier: Programming Language :: Python :: 2.7
Classifier: Programming Language :: Python :: 3
Classifier: Programming Language :: Python :: 3.4
Classifier: Programming Language :: Python :: 3.5
Classifier: Programming Language :: Python :: 3.6
Classifier: Programming Language :: Python :: 3.7
Classifier: Programming Language :: Python :: 3.8
Classifier: Programming Language :: Python :: 3.9
Classifier: Programming Language :: Python :: 3.10
Classifier: Programming Language :: Python :: 3.11
Classifier: Topic :: Multimedia :: Sound/Audio
Classifier: Topic :: Multimedia :: Video
Classifier: Topic :: Utilities
Requires-Dist: construct (==2.8.8)
Project-URL: Repository, https://github.com/rlaphoenix/pymp4
